dzee_helper.py
automslc-5.1.data/scripts/automslc
deezer/__init__.py
deezer/deezer2.py
deezer/utils.py
automslc-5.1.dist-info/LICENSE
automslc-5.1.dist-info/METADATA
automslc-5.1.dist-info/WHEEL
automslc-5.1.dist-info/top_level.txt
automslc-5.1.dist-info/RECORD
