Metadata-Version: 2.2
Name: automslc
Version: 5.1
Summary: A Des of AutoMSLC
Home-page: https://github.com/vtandroid/dokr
Author: Thanh Hoa
Author-email: getmoneykhmt3@gmail.com
Classifier: Programming Language :: Python :: 3
Classifier: License :: OSI Approved :: MIT License
Classifier: Operating System :: OS Independent
License-File: LICENSE
Requires-Dist: requests
Requires-Dist: click
Requires-Dist: pycryptodome
Requires-Dist: pycryptodomex
Requires-Dist: gbak
Dynamic: author
Dynamic: author-email
Dynamic: classifier
Dynamic: description
Dynamic: description-content-type
Dynamic: home-page
Dynamic: requires-dist
Dynamic: summary
